Metadata-Version: 2.1
Name: debug-world-swt
Version: 0.0.1
Summary: PyPI Tutorial
Home-page: https://github.com/
Author: yutingshao
Author-email: 1219859151@qq.com
License: UNKNOWN
Platform: UNKNOWN
Classifier: Programming Language :: Python :: 3
Classifier: License :: OSI Approved :: MIT License
Classifier: Operating System :: OS Independent
Requires-Python: >=3
